quantum_pen/__init__.py
quantum_pen/main.py
quantum_pen-0.1.2.dist-info/licenses/LICENSE
quantum_pen-0.1.2.dist-info/METADATA
quantum_pen-0.1.2.dist-info/WHEEL
quantum_pen-0.1.2.dist-info/entry_points.txt
quantum_pen-0.1.2.dist-info/top_level.txt
quantum_pen-0.1.2.dist-info/RECORD
