Metadata-Version: 2.4
Name: quantum-pen
Version: 0.1.2
Summary: Stories are not written, but discovered.
Requires-Python: >=3.12
License-File: LICENSE
Requires-Dist: openai>=1.106.1
Requires-Dist: redis>=6.4.0
Requires-Dist: python-dotenv>=1.1.1
Dynamic: license-file
